circular_buffer/__init__.py
circular_buffer/circular_buffer.py
circular_buffer/numba_mock.py
circular_buffer-0.2.0.dist-info/LICENSE
circular_buffer-0.2.0.dist-info/METADATA
circular_buffer-0.2.0.dist-info/WHEEL
circular_buffer-0.2.0.dist-info/top_level.txt
circular_buffer-0.2.0.dist-info/RECORD
